auto/__init__.py
auto/icon_thread.py
auto/icon_thread_test.py
automonic-0.0.2.dist-info/METADATA
automonic-0.0.2.dist-info/WHEEL
automonic-0.0.2.dist-info/license.txt
automonic-0.0.2.dist-info/top_level.txt
automonic-0.0.2.dist-info/RECORD
